{
    "DOGEUSDT": {
        "buyOrders": [
            {
                "price": "0.23",
                "qty": "72"
            },
            {
                "price": "0.22",
                "qty": "72"
            },
            {
                "price": "0.21",
                "qty": "72"
            },
            {
                "price": "0.2",
                "qty": "100",
                "orderId": 9025075837
            }
        ],
        "sellOrders": [
            {
                "price": "0.27",
                "qty": "70"
            },
            {
                "price": "0.28",
                "qty": "70"
            }
        ]
    }
}